README.md
setup.py
data/RNA16.dbn
data/RNA16.react
data/RNA20.dbn
data/RNA20.react
data/RNA21.csv
data/RNA21.dbn
data/__init__.py
data/RNA16_original_data/RNA16_format.py
data/RNA16_original_data/RNA16_dotbracket/23sRNA.bpseq
data/RNA16_original_data/RNA16_dotbracket/5srRNA.bpseq
data/RNA16_original_data/RNA16_dotbracket/ADDRSW.bpseq
data/RNA16_original_data/RNA16_dotbracket/Adenin.bpseq
data/RNA16_original_data/RNA16_dotbracket/GLYCFN.bpseq
data/RNA16_original_data/RNA16_dotbracket/MDLOOP.bpseq
data/RNA16_original_data/RNA16_dotbracket/R009.bpseq
data/RNA16_original_data/RNA16_dotbracket/RNAsp.bpseq
data/RNA16_original_data/RNA16_dotbracket/TRP4.bpseq
data/RNA16_original_data/RNA16_dotbracket/Z-CID.bpseq
data/RNA16_original_data/RNA16_dotbracket/Z-GLY.bpseq
data/RNA16_original_data/RNA16_dotbracket/Z-HCV.bpseq
data/RNA16_original_data/RNA16_dotbracket/p546.bpseq
data/RNA16_original_data/RNA16_dotbracket/srRNA-8.bpseq
data/RNA16_original_data/RNA16_dotbracket/tRNA Asp.bpseq
data/RNA16_original_data/RNA16_dotbracket/tRNA-phe.bpseq
data/RNA16_original_data/RNA16_sequences/23sRNA.seq
data/RNA16_original_data/RNA16_sequences/5srRNA.seq
data/RNA16_original_data/RNA16_sequences/ADDRSW.seq
data/RNA16_original_data/RNA16_sequences/GLYCFN.seq
data/RNA16_original_data/RNA16_sequences/MDLOOP.seq
data/RNA16_original_data/RNA16_sequences/R009.seq
data/RNA16_original_data/RNA16_sequences/RNAsep.seq
data/RNA16_original_data/RNA16_sequences/TRP4.seq
data/RNA16_original_data/RNA16_sequences/Z-CIDGMP.seq
data/RNA16_original_data/RNA16_sequences/Z-GLY.seq
data/RNA16_original_data/RNA16_sequences/ZHCV.seq
data/RNA16_original_data/RNA16_sequences/adenin.seq
data/RNA16_original_data/RNA16_sequences/p546.seq
data/RNA16_original_data/RNA16_sequences/sRNA.seq
data/RNA16_original_data/RNA16_sequences/tRNAPhe.seq
data/RNA16_original_data/RNA16_sequences/trna-asp.seq
data/RNA16_original_data/RNA16_shape/23sRNA.shape
data/RNA16_original_data/RNA16_shape/5srRNA.shape
shaker_rna.egg-info/PKG-INFO
shaker_rna.egg-info/SOURCES.txt
shaker_rna.egg-info/dependency_links.txt
shaker_rna.egg-info/entry_points.txt
shaker_rna.egg-info/requires.txt
shaker_rna.egg-info/top_level.txt