Metadata-Version: 1.0
Name: shaker-rna
Version: 0.0.190
Summary: RNA SHAPE (or other structure prediction protocol) prediction via graph kernel
Home-page: https://github.com/smautner/
Author: Stefan Mautner
Author-email: myl4stn4m3@cs.uni-freiburg.de
License: LICENSE
Platform: UNKNOWN
